poetry_audit_plugin/__init__.py
poetry_audit_plugin/command.py
poetry_audit_plugin/constants.py
poetry_audit_plugin/errors.py
poetry_audit_plugin/plugin.py
poetry_audit_plugin/safety.py
poetry_audit_plugin-0.4.0.dist-info/LICENSE
poetry_audit_plugin-0.4.0.dist-info/METADATA
poetry_audit_plugin-0.4.0.dist-info/WHEEL
poetry_audit_plugin-0.4.0.dist-info/entry_points.txt
poetry_audit_plugin-0.4.0.dist-info/RECORD
