Metadata-Version: 2.1
Name: poetry-audit-plugin
Version: 0.4.0
Summary: Poetry plugin for checking security vulnerabilities in dependencies
Home-page: https://github.com/opeco17/poetry-audit-plugin
Keywords: poetry,vulnerabilities,security,audit
Author: opeco17
Author-email: opeco17@gmail.com
Requires-Python: >=3.8,<4.0
Classifier: Intended Audience :: Developers
Classifier: Intended Audience :: Information Technology
Classifier: Intended Audience :: System Administrators
Classifier: License :: OSI Approved :: MIT License
Classifier: Operating System :: OS Independent
Classifier: Programming Language :: Python
Classifier: Programming Language :: Python :: 3
Classifier: Programming Language :: Python :: 3.8
Classifier: Programming Language :: Python :: 3.9
Classifier: Programming Language :: Python :: 3.10
Classifier: Programming Language :: Python :: 3.11
Classifier: Programming Language :: Python :: 3.12
Classifier: Programming Language :: Python :: 3 :: Only
Classifier: Topic :: Software Development
Classifier: Topic :: Software Development :: Build Tools
Classifier: Topic :: Software Development :: Libraries
Classifier: Topic :: Software Development :: Libraries :: Python Modules
Classifier: Topic :: System :: Archiving :: Packaging
Classifier: Topic :: System :: Installation/Setup
Classifier: Topic :: System :: Software Distribution
Requires-Dist: poetry (>=1.6.1,<2.0.0)
Requires-Dist: safety (>=3.0.0,<4.0.0)
Project-URL: Repository, https://github.com/opeco17/poetry-audit-plugin
